tomark/__init__.py
tomark/tomark.py
tomark-0.1.4.dist-info/METADATA
tomark-0.1.4.dist-info/RECORD
tomark-0.1.4.dist-info/WHEEL
tomark-0.1.4.dist-info/top_level.txt
