Metadata-Version: 2.1
Name: tomark
Version: 0.1.4
Summary: Convert a list of dictionaries to a markdown formatted table.
Home-page: https://github.com/codazoda/tomark
Author: Joel Dare
Author-email: joel@joeldare.com
License: UNKNOWN
Platform: UNKNOWN
Classifier: Development Status :: 3 - Alpha
Classifier: Intended Audience :: Developers
Classifier: Environment :: Web Environment
Classifier: License :: OSI Approved :: MIT License
Classifier: Natural Language :: English
Classifier: Programming Language :: Python :: 3
Classifier: Topic :: Text Processing :: Markup
Classifier: Operating System :: OS Independent
